mxm/types/__init__.py
mxm/types/py.typed
mxm_types-0.1.1.dist-info/METADATA
mxm_types-0.1.1.dist-info/WHEEL
mxm_types-0.1.1.dist-info/licenses/LICENSE
mxm_types-0.1.1.dist-info/RECORD
