Metadata-Version: 2.4
Name: mxm-types
Version: 0.1.1
Summary: Shared typing primitives for Money Ex Machina.
License: MIT
License-File: LICENSE
Keywords: money-ex-machina,typing,json,types,pep561
Author: mxm
Author-email: contact@moneyexmachina.com
Requires-Python: >=3.13,<3.15
Classifier: Development Status :: 3 - Alpha
Classifier: Intended Audience :: Developers
Classifier: License :: OSI Approved :: MIT License
Classifier: Programming Language :: Python :: 3
Classifier: Programming Language :: Python :: 3.13
Classifier: Programming Language :: Python :: 3.14
Classifier: Topic :: Software Development :: Libraries :: Python Modules
Classifier: Typing :: Typed
Project-URL: Homepage, https://github.com/moneyexmachina/
Project-URL: Issues, https://github.com/moneyexmachina/mxm-types/issues
Project-URL: Repository, https://github.com/moneyexmachina/mxm-types
